[
  {
    "id": "evac-mandaluyong-001",
    "name": "Mandaluyong High School Gym",
    "location": {
      "barangayCode": "137404001",
      "barangayName": "Addition Hills",
      "cityMunicipality": "Mandaluyong City",
      "province": "Metro Manila",
      "region": "NCR"
    },
    "lat": 14.5845,
    "lng": 121.0421,
    "capacity": 500,
    "status": "OPEN",
    "statusUpdatedAt": "2026-07-01T08:00:00.000Z",
    "statusSource": "LGU_ADMIN"
  },
  {
    "id": "evac-mandaluyong-002",
    "name": "Addition Hills Covered Court",
    "location": {
      "barangayCode": "137404001",
      "barangayName": "Addition Hills",
      "cityMunicipality": "Mandaluyong City",
      "province": "Metro Manila",
      "region": "NCR"
    },
    "lat": 14.5821,
    "lng": 121.0398,
    "capacity": 200,
    "status": "UNKNOWN",
    "statusUpdatedAt": "2026-06-20T08:00:00.000Z",
    "statusSource": "DEFAULT_UNKNOWN"
  },
  {
    "id": "evac-makati-001",
    "name": "Bel-Air Elementary School",
    "location": {
      "barangayCode": "137602001",
      "barangayName": "Bel-Air",
      "cityMunicipality": "Makati City",
      "province": "Metro Manila",
      "region": "NCR"
    },
    "lat": 14.5558,
    "lng": 121.0256,
    "capacity": 350,
    "status": "OPEN",
    "statusUpdatedAt": "2026-07-01T06:30:00.000Z",
    "statusSource": "LGU_ADMIN"
  },
  {
    "id": "evac-makati-002",
    "name": "Makati Sports Club Evacuation Area",
    "location": {
      "barangayCode": "137602002",
      "barangayName": "Poblacion",
      "cityMunicipality": "Makati City",
      "province": "Metro Manila",
      "region": "NCR"
    },
    "lat": 14.5662,
    "lng": 121.0325,
    "capacity": 150,
    "status": "FULL",
    "statusUpdatedAt": "2026-06-29T10:00:00.000Z",
    "statusSource": "COMMUNITY_REPORT"
  },
  {
    "id": "evac-manila-001",
    "name": "Rizal Memorial Sports Complex",
    "location": {
      "barangayCode": "137501002",
      "barangayName": "Malate",
      "cityMunicipality": "Manila",
      "province": "Metro Manila",
      "region": "NCR"
    },
    "lat": 14.5623,
    "lng": 120.9931,
    "capacity": 800,
    "status": "OPEN",
    "statusUpdatedAt": "2026-07-01T04:00:00.000Z",
    "statusSource": "LGU_ADMIN"
  },
  {
    "id": "evac-taguig-001",
    "name": "Taguig City University Gym",
    "location": {
      "barangayCode": "137403002",
      "barangayName": "Lower Bicutan",
      "cityMunicipality": "Taguig City",
      "province": "Metro Manila",
      "region": "NCR"
    },
    "lat": 14.4891,
    "lng": 121.0512,
    "capacity": 600,
    "status": "CLOSED",
    "statusUpdatedAt": "2026-07-01T03:00:00.000Z",
    "statusSource": "LGU_ADMIN"
  },
  {
    "id": "evac-cebu-001",
    "name": "Cebu City Sports Center",
    "location": {
      "barangayCode": "072217001",
      "barangayName": "Lahug",
      "cityMunicipality": "Cebu City",
      "province": "Cebu",
      "region": "Region VII"
    },
    "lat": 10.3245,
    "lng": 123.8998,
    "capacity": 1000,
    "status": "OPEN",
    "statusUpdatedAt": "2026-06-30T12:00:00.000Z",
    "statusSource": "LGU_ADMIN"
  },
  {
    "id": "evac-cebu-002",
    "name": "Guadalupe Barangay Hall",
    "location": {
      "barangayCode": "072217002",
      "barangayName": "Guadalupe",
      "cityMunicipality": "Cebu City",
      "province": "Cebu",
      "region": "Region VII"
    },
    "lat": 10.3161,
    "lng": 123.8867,
    "capacity": 150,
    "status": "UNKNOWN",
    "statusUpdatedAt": "2026-06-15T08:00:00.000Z",
    "statusSource": "DEFAULT_UNKNOWN"
  },
  {
    "id": "evac-albay-001",
    "name": "Legazpi City Convention Center",
    "location": {
      "barangayCode": "043405001",
      "barangayName": "San Roque",
      "cityMunicipality": "Legazpi City",
      "province": "Albay",
      "region": "Region V"
    },
    "lat": 13.1425,
    "lng": 123.7356,
    "capacity": 400,
    "status": "OPEN",
    "statusUpdatedAt": "2026-06-28T14:00:00.000Z",
    "statusSource": "LGU_ADMIN"
  },
  {
    "id": "evac-remote-001",
    "name": "San Juan City Gymnasium",
    "location": {
      "barangayCode": "137601001",
      "barangayName": "Addition Hills",
      "cityMunicipality": "San Juan City",
      "province": "Metro Manila",
      "region": "NCR"
    },
    "lat": 14.6025,
    "lng": 121.0395,
    "capacity": 300,
    "status": "OPEN",
    "statusUpdatedAt": "2026-07-01T07:00:00.000Z",
    "statusSource": "LGU_ADMIN"
  }
]
